{
  "papers": [
    {
      "id": "history-electrophysiology",
      "title": "History of Electrophysiology and the Patch Clamp",
      "authors": [],
      "journal": null,
      "volume": null,
      "issue": null,
      "pages": null,
      "year": null,
      "doi": null,
      "topics": ["historia", "electrofisiología", "patch clamp", "canales iónicos"],
      "filename": "History of Electrophysiology and the Patch Clamp.pdf",
      "abstract": "Documento sobre la historia de la electrofisiología y el desarrollo de la técnica de patch clamp."
    }
  ]
}
